{
	"configurations" : 
	[
		{
			"directories" : 
			[
				{
					"build" : ".",
					"jsonFile" : "directory-.-Debug-d0094a50bb2071803777.json",
					"minimumCMakeVersion" : 
					{
						"string" : "3.27"
					},
					"projectIndex" : 0,
					"source" : ".",
					"targetIndexes" : 
					[
						0
					]
				}
			],
			"name" : "Debug",
			"projects" : 
			[
				{
					"directoryIndexes" : 
					[
						0
					],
					"name" : "Lab1_Arkanoid",
					"targetIndexes" : 
					[
						0
					]
				}
			],
			"targets" : 
			[
				{
					"directoryIndex" : 0,
					"id" : "Lab1_Arkanoid::@6890427a1f51a3e7e1df",
					"jsonFile" : "target-Lab1_Arkanoid-Debug-c65055f6218b680316f2.json",
					"name" : "Lab1_Arkanoid",
					"projectIndex" : 0
				}
			]
		}
	],
	"kind" : "codemodel",
	"paths" : 
	{
		"build" : "D:/GitHub/University/Programming technologies/Lab1-Arkanoid/cmake-build-debug",
		"source" : "D:/GitHub/University/Programming technologies/Lab1-Arkanoid"
	},
	"version" : 
	{
		"major" : 2,
		"minor" : 6
	}
}
